figmaflet/__init__.py
figmaflet/cli.py
figmaflet/generateUI.py
figmaflet/template.py
figmaflet/utils.py
figmaflet/figma/endpoints.py
figmaflet/figma/frame.py
figmaflet/figma/node.py
figmaflet/figma/vector_elements.py
figmaflet/gui/__main__.py
generated_ui/main.py
figmaflet-0.0.6.dist-info/LICENSE
figmaflet-0.0.6.dist-info/METADATA
figmaflet-0.0.6.dist-info/WHEEL
figmaflet-0.0.6.dist-info/entry_points.txt
figmaflet-0.0.6.dist-info/top_level.txt
figmaflet-0.0.6.dist-info/RECORD
