Metadata-Version: 2.2
Name: figmaflet
Version: 0.0.6
Summary: A tool to generate Flet UI from Figma designs.
Author-email: Benit Mulindwa <mulindwabenit@gmail.com>
License: Apache-2.0 license
Project-URL: Homepage, https://github.com/Benitmulindwa/figmaflet
Keywords: flet,drag-and-drop,figma,ui,easy
Classifier: Programming Language :: Python :: 3
Classifier: License :: OSI Approved :: Apache Software License
Classifier: Operating System :: OS Independent
Requires-Python: >=3.8
License-File: LICENSE
Requires-Dist: jinja2
Requires-Dist: requests
Requires-Dist: pillow
